setup.py
emailahoy/__init__.py
emailahoy/email.py
python_emailahoy.egg-info/PKG-INFO
python_emailahoy.egg-info/SOURCES.txt
python_emailahoy.egg-info/dependency_links.txt
python_emailahoy.egg-info/top_level.txt