Metadata-Version: 1.1
Name: python-emailahoy
Version: 0.0.6
Summary: A Python email utility that verifies existence of an email address
Home-page: https://github.com/un33k/python-emailahoy
Author: Val Neekman
Author-email: info@neekware.com
License: BSD
Platform: UNKNOWN
Classifier: Development Status :: 3 - Alpha
Classifier: Intended Audience :: Developers
Classifier: License :: OSI Approved :: BSD License
Classifier: Operating System :: POSIX
Classifier: Programming Language :: Python
Classifier: Topic :: Software Development :: Libraries :: Python Modules
Classifier: Topic :: Communications :: Email
